{ "compressionlevel":-1,
 "height":10,
 "infinite":false,
 "layers":[
        {
         "data":[181, 182, 183, 184, 185, 186, 187, 188, 189, 190, 1359, 1359, 1359, 1645, 1645,
            237, 1645, 1645, 240, 241, 1533, 1704, 1533, 1533, 246, 1359, 1359, 1359, 1359, 1359,
            1533, 1533, 1645, 1645, 185, 186, 1704, 1704, 1533, 190, 1359, 1359, 1422, 2261, 1359,
            237, 238, 239, 240, 241, 242, 243, 1533, 1533, 246, 1359, 1139, 1139, 1139, 1139,
            293, 1533, 295, 1533, 1533, 298, 299, 300, 1533, 302, 1645, 1139, 1139, 1139, 1704,
            349, 1533, 351, 352, 353, 1533, 355, 356, 1533, 358, 1645, 1645, 1139, 1139, 1139,
            405, 1533, 1533, 1533, 1533, 1533, 1533, 1533, 1533, 414, 2261, 1139, 1139, 1139, 1139,
            461, 462, 463, 464, 465, 466, 467, 468, 469, 470, 2261, 1139, 1139, 2261, 2261,
            0, 0, 0, 0, 0, 0, 0, 0, 0, 0, 0, 0, 0, 0, 0,
            0, 0, 0, 0, 0, 0, 0, 0, 0, 0, 0, 0, 0, 0, 0],
         "height":10,
         "id":1,
         "name":"Sky",
         "opacity":1,
         "type":"tilelayer",
         "visible":true,
         "width":15,
         "x":0,
         "y":0
        }, 
        {
         "data":[0, 0, 0, 0, 0, 0, 0, 0, 0, 0, 0, 0, 0, 1646, 1646,
            0, 0, 0, 0, 0, 0, 0, 0, 0, 0, 0, 0, 0, 2094, 2094,
            0, 0, 0, 0, 0, 0, 0, 0, 0, 0, 0, 0, 0, 2205, 2094,
            0, 0, 0, 0, 0, 0, 0, 0, 0, 0, 0, 0, 0, 2094, 2094,
            0, 0, 0, 0, 0, 0, 0, 0, 0, 0, 0, 0, 0, 2094, 1646,
            0, 0, 0, 0, 0, 0, 0, 0, 0, 0, 0, 0, 0, 2094, 2094,
            0, 0, 0, 0, 0, 0, 0, 0, 0, 0, 0, 0, 0, 2094, 2094,
            0, 0, 0, 0, 0, 0, 0, 0, 0, 0, 0, 0, 0, 1810, 1810,
            23, 23, 23, 23, 23, 23, 23, 23, 23, 23, 23, 23, 23, 23, 23,
            123, 123, 123, 123, 123, 123, 123, 123, 123, 123, 123, 123, 123, 123, 123],
         "height":10,
         "id":2,
         "name":"Ground",
         "opacity":1,
         "type":"tilelayer",
         "visible":true,
         "width":15,
         "x":0,
         "y":0
        }, 
        {
         "data":[45, 0, 0, 0, 0, 0, 0, 0, 0, 0, 0, 0, 0, 0, 0,
            0, 0, 0, 0, 0, 0, 0, 0, 0, 0, 0, 0, 0, 0, 0,
            0, 0, 0, 0, 0, 0, 0, 0, 0, 0, 0, 0, 0, 0, 0,
            0, 0, 0, 0, 0, 0, 0, 0, 0, 0, 0, 0, 0, 0, 0,
            0, 0, 0, 0, 0, 0, 0, 0, 0, 0, 0, 0, 0, 0, 0,
            0, 0, 0, 0, 0, 0, 0, 0, 0, 0, 0, 0, 0, 0, 0,
            0, 0, 0, 0, 0, 0, 0, 0, 0, 0, 0, 0, 0, 0, 0,
            0, 0, 0, 0, 0, 0, 0, 0, 0, 0, 0, 0, 0, 0, 0,
            0, 0, 0, 0, 0, 0, 0, 0, 0, 0, 0, 0, 0, 0, 0,
            0, 0, 0, 0, 0, 0, 0, 0, 0, 0, 0, 0, 0, 0, 0],
         "height":10,
         "id":3,
         "name":"oneLife",
         "opacity":1,
         "type":"tilelayer",
         "visible":true,
         "width":15,
         "x":0,
         "y":0
        }, 
        {
         "data":[45, 45, 0, 0, 0, 0, 0, 0, 0, 0, 0, 0, 0, 0, 0,
            0, 0, 0, 0, 0, 0, 0, 0, 0, 0, 0, 0, 0, 0, 0,
            0, 0, 0, 0, 0, 0, 0, 0, 0, 0, 0, 0, 0, 0, 0,
            0, 0, 0, 0, 0, 0, 0, 0, 0, 0, 0, 0, 0, 0, 0,
            0, 0, 0, 0, 0, 0, 0, 0, 0, 0, 0, 0, 0, 0, 0,
            0, 0, 0, 0, 0, 0, 0, 0, 0, 0, 0, 0, 0, 0, 0,
            0, 0, 0, 0, 0, 0, 0, 0, 0, 0, 0, 0, 0, 0, 0,
            0, 0, 0, 0, 0, 0, 0, 0, 0, 0, 0, 0, 0, 0, 0,
            0, 0, 0, 0, 0, 0, 0, 0, 0, 0, 0, 0, 0, 0, 0,
            0, 0, 0, 0, 0, 0, 0, 0, 0, 0, 0, 0, 0, 0, 0],
         "height":10,
         "id":4,
         "name":"twoLife",
         "opacity":1,
         "type":"tilelayer",
         "visible":true,
         "width":15,
         "x":0,
         "y":0
        }, 
        {
         "data":[45, 45, 45, 0, 0, 0, 0, 0, 0, 0, 0, 0, 0, 0, 0,
            0, 0, 0, 0, 0, 0, 0, 0, 0, 0, 0, 0, 0, 0, 0,
            0, 0, 0, 0, 0, 0, 0, 0, 0, 0, 0, 0, 0, 0, 0,
            0, 0, 0, 0, 0, 0, 0, 0, 0, 0, 0, 0, 0, 0, 0,
            0, 0, 0, 0, 0, 0, 0, 0, 0, 0, 0, 0, 0, 0, 0,
            0, 0, 0, 0, 0, 0, 0, 0, 0, 0, 0, 0, 0, 0, 0,
            0, 0, 0, 0, 0, 0, 0, 0, 0, 0, 0, 0, 0, 0, 0,
            0, 0, 0, 0, 0, 0, 0, 0, 0, 0, 0, 0, 0, 0, 0,
            0, 0, 0, 0, 0, 0, 0, 0, 0, 0, 0, 0, 0, 0, 0,
            0, 0, 0, 0, 0, 0, 0, 0, 0, 0, 0, 0, 0, 0, 0],
         "height":10,
         "id":5,
         "name":"threeLife",
         "opacity":1,
         "type":"tilelayer",
         "visible":true,
         "width":15,
         "x":0,
         "y":0
        }],
 "nextlayerid":6,
 "nextobjectid":1,
 "orientation":"orthogonal",
 "renderorder":"right-down",
 "tiledversion":"1.10.2",
 "tileheight":18,
 "tilesets":[
        {
         "columns":20,
         "firstgid":1,
         "image":"tilemap_packed.png",
         "imageheight":162,
         "imagewidth":360,
         "margin":0,
         "name":"objects",
         "spacing":0,
         "tilecount":180,
         "tileheight":18,
         "tilewidth":18
        }, 
        {
         "columns":56,
         "firstgid":181,
         "image":"backgroundForest.png",
         "imageheight":1024,
         "imagewidth":1024,
         "margin":0,
         "name":"sky",
         "spacing":0,
         "tilecount":3136,
         "tileheight":18,
         "tilewidth":18
        }, 
        {
         "firstgid":3317,
         "source":"..\/..\/..\/KennyAssets\/kenney_pixel-platformer\/Tiled\/tileset-tiles.tsx"
        }],
 "tilewidth":18,
 "type":"map",
 "version":"1.10",
 "width":15
}